{
  "en": {
    "heading": "GIVE US A SHOUT",
    "subheading": "We are ready to lead you into the future of personal finance",
    "ouraddress": "Our Address",
    "getintouch": "Get in Touch",
    "street": "114 King Street,",
    "city": " Melbourne, Victoria,",
    "postcode": " 3000",
    "country": "Australia"
  },
  "de": {
    "heading": "RUFEN SIE UNS AN",
    "subheading": "Starten Sie mit uns noch heute in Ihre persönliche finanzielle Zukunft",
    "ouraddress": "Unsere Adresse",
    "getintouch": "Nehmen Sie Kontakt auf",
    "street": "114 King Street,",
    "city": " Melbourne, Victoria,",
    "postcode": " 3000",
    "country": "Australia"
  },
  "es": {}
}
